{
  "updated": "2026-07-07T10:23:55Z",
  "source": "Trading 212 live API",
  "currency": "EUR",
  "fxRates": {
    "EUR": 1,
    "USD": 1.1415
  },
  "account": {
    "id": 30881486,
    "currencyCode": "EUR"
  },
  "cash": {
    "free": 1026.31,
    "invested": 131.15,
    "ppl": -0.85,
    "result": 416.62,
    "total": 1156.96,
    "pieCash": 0.35,
    "blocked": 0
  },
  "totals": {
    "positionCount": 14,
    "marketValue": 130.3,
    "costBasis": 131.15,
    "unrealizedPL": -0.85,
    "unrealizedPLPct": -0.65,
    "accountValue": 1156.96
  },
  "positions": [
    {
      "ticker": "TM_US_EQ",
      "nativeCurrency": "USD",
      "quantity": 0.1358418,
      "averagePrice": 244.99086437,
      "currentPrice": 181.45,
      "nativeCurrencyValue": 24.65,
      "costBasis": 30.65,
      "marketValue": 21.59,
      "unrealizedPL": -9.06,
      "unrealizedPLPct": -29.56,
      "fxPpl": -1.51,
      "initialFillDate": "2024-03-19T18:49:19.000+02:00",
      "pieQuantity": 0,
      "frontend": "IOS",
      "allocationPercent": 16.57
    },
    {
      "ticker": "SPCX_US_EQ",
      "nativeCurrency": "USD",
      "quantity": 0.10425283,
      "averagePrice": 173.52046942,
      "currentPrice": 158.33,
      "nativeCurrencyValue": 16.51,
      "costBasis": 15.65,
      "marketValue": 14.46,
      "unrealizedPL": -1.19,
      "unrealizedPLPct": -7.6,
      "fxPpl": 0.2,
      "initialFillDate": "2026-06-12T19:59:07.000+03:00",
      "pieQuantity": 0,
      "frontend": "IOS",
      "allocationPercent": 11.1
    },
    {
      "ticker": "CSCO_US_EQ",
      "nativeCurrency": "USD",
      "quantity": 0.10824462,
      "averagePrice": 76.4934091,
      "currentPrice": 113.67,
      "nativeCurrencyValue": 12.3,
      "costBasis": 7.1,
      "marketValue": 10.78,
      "unrealizedPL": 3.68,
      "unrealizedPLPct": 51.84,
      "fxPpl": 0.16,
      "initialFillDate": "2026-01-05T16:30:10.000+02:00",
      "pieQuantity": 0.10824462,
      "frontend": "AUTOINVEST",
      "allocationPercent": 8.27
    },
    {
      "ticker": "GOOG_US_EQ",
      "nativeCurrency": "USD",
      "quantity": 0.0293086,
      "averagePrice": 317.99540067,
      "currentPrice": 366.89,
      "nativeCurrencyValue": 10.75,
      "costBasis": 7.99,
      "marketValue": 9.42,
      "unrealizedPL": 1.43,
      "unrealizedPLPct": 17.9,
      "fxPpl": 0.18,
      "initialFillDate": "2026-01-05T16:30:00.000+02:00",
      "pieQuantity": 0.0293086,
      "frontend": "AUTOINVEST",
      "allocationPercent": 7.23
    },
    {
      "ticker": "AMZN_US_EQ",
      "nativeCurrency": "USD",
      "quantity": 0.04069834,
      "averagePrice": 229.00196912,
      "currentPrice": 247.75,
      "nativeCurrencyValue": 10.08,
      "costBasis": 7.99,
      "marketValue": 8.83,
      "unrealizedPL": 0.84,
      "unrealizedPLPct": 10.51,
      "fxPpl": 0.17,
      "initialFillDate": "2026-01-05T16:30:02.000+02:00",
      "pieQuantity": 0.04069834,
      "frontend": "AUTOINVEST",
      "allocationPercent": 6.78
    },
    {
      "ticker": "AAPL_US_EQ",
      "nativeCurrency": "USD",
      "quantity": 0.03057359,
      "averagePrice": 182.8375405,
      "currentPrice": 314.55,
      "nativeCurrencyValue": 9.62,
      "costBasis": 5.14,
      "marketValue": 8.42,
      "unrealizedPL": 3.28,
      "unrealizedPLPct": 63.75,
      "fxPpl": -0.24,
      "initialFillDate": "2024-02-21T16:30:02.000+02:00",
      "pieQuantity": 0.03057359,
      "frontend": "IOS",
      "allocationPercent": 6.46
    },
    {
      "ticker": "AVGO_US_EQ",
      "nativeCurrency": "USD",
      "quantity": 0.02625477,
      "averagePrice": 354.98311354,
      "currentPrice": 365.92,
      "nativeCurrencyValue": 9.61,
      "costBasis": 7.99,
      "marketValue": 8.42,
      "unrealizedPL": 0.43,
      "unrealizedPLPct": 5.38,
      "fxPpl": 0.18,
      "initialFillDate": "2026-01-05T16:30:05.000+02:00",
      "pieQuantity": 0.02625477,
      "frontend": "AUTOINVEST",
      "allocationPercent": 6.46
    },
    {
      "ticker": "IBM_US_EQ",
      "nativeCurrency": "USD",
      "quantity": 0.03147558,
      "averagePrice": 296.10256586,
      "currentPrice": 303.41,
      "nativeCurrencyValue": 9.55,
      "costBasis": 7.99,
      "marketValue": 8.37,
      "unrealizedPL": 0.38,
      "unrealizedPLPct": 4.76,
      "fxPpl": 0.18,
      "initialFillDate": "2026-01-05T16:30:05.000+02:00",
      "pieQuantity": 0.03147558,
      "frontend": "AUTOINVEST",
      "allocationPercent": 6.42
    },
    {
      "ticker": "NVDA_US_EQ",
      "nativeCurrency": "USD",
      "quantity": 0.04858427,
      "averagePrice": 138.31637277,
      "currentPrice": 194.04,
      "nativeCurrencyValue": 9.43,
      "costBasis": 6.2,
      "marketValue": 8.26,
      "unrealizedPL": 2.06,
      "unrealizedPLPct": 33.23,
      "fxPpl": -0.31,
      "initialFillDate": "2024-06-17T22:05:16.000+03:00",
      "pieQuantity": 0.04858427,
      "frontend": "IOS",
      "allocationPercent": 6.34
    },
    {
      "ticker": "FB_US_EQ",
      "nativeCurrency": "USD",
      "quantity": 0.01429698,
      "averagePrice": 651.88592276,
      "currentPrice": 607.12,
      "nativeCurrencyValue": 8.68,
      "costBasis": 7.99,
      "marketValue": 7.6,
      "unrealizedPL": -0.39,
      "unrealizedPLPct": -4.88,
      "fxPpl": 0.17,
      "initialFillDate": "2026-01-05T16:30:04.000+02:00",
      "pieQuantity": 0.01429698,
      "frontend": "AUTOINVEST",
      "allocationPercent": 5.83
    },
    {
      "ticker": "QCOM_US_EQ",
      "nativeCurrency": "USD",
      "quantity": 0.04718182,
      "averagePrice": 175.49132272,
      "currentPrice": 182.7,
      "nativeCurrencyValue": 8.62,
      "costBasis": 7.1,
      "marketValue": 7.55,
      "unrealizedPL": 0.45,
      "unrealizedPLPct": 6.34,
      "fxPpl": 0.15,
      "initialFillDate": "2026-01-05T16:30:01.000+02:00",
      "pieQuantity": 0.04718182,
      "frontend": "AUTOINVEST",
      "allocationPercent": 5.79
    },
    {
      "ticker": "MSFT_US_EQ",
      "nativeCurrency": "USD",
      "quantity": 0.01746038,
      "averagePrice": 474.21648326,
      "currentPrice": 392.4,
      "nativeCurrencyValue": 6.85,
      "costBasis": 7.1,
      "marketValue": 6,
      "unrealizedPL": -1.1,
      "unrealizedPLPct": -15.49,
      "fxPpl": 0.15,
      "initialFillDate": "2026-01-05T16:30:04.000+02:00",
      "pieQuantity": 0.01746038,
      "frontend": "AUTOINVEST",
      "allocationPercent": 4.6
    },
    {
      "ticker": "TSLA_US_EQ",
      "nativeCurrency": "USD",
      "quantity": 0.01616267,
      "averagePrice": 447.94579113,
      "currentPrice": 416.08,
      "nativeCurrencyValue": 6.72,
      "costBasis": 6.21,
      "marketValue": 5.89,
      "unrealizedPL": -0.32,
      "unrealizedPLPct": -5.15,
      "fxPpl": 0.13,
      "initialFillDate": "2026-01-05T16:30:01.000+02:00",
      "pieQuantity": 0.01616267,
      "frontend": "AUTOINVEST",
      "allocationPercent": 4.52
    },
    {
      "ticker": "PLTR_US_EQ",
      "nativeCurrency": "USD",
      "quantity": 0.04140542,
      "averagePrice": 174.85633523,
      "currentPrice": 134.43,
      "nativeCurrencyValue": 5.57,
      "costBasis": 6.21,
      "marketValue": 4.88,
      "unrealizedPL": -1.33,
      "unrealizedPLPct": -21.43,
      "fxPpl": 0.13,
      "initialFillDate": "2026-01-05T16:30:01.000+02:00",
      "pieQuantity": 0.04140542,
      "frontend": "AUTOINVEST",
      "allocationPercent": 3.75
    }
  ]
}
